{
    "1443314822182732010": {
        "1320349118102769767": {
            "xp": 52,
            "level": 0
        },
        "1435974392810307604": {
            "xp": 127,
            "level": 2
        }
    },
    "1431700832671240264": {
        "1223101387316002917": {
            "xp": 60,
            "level": 0
        },
        "1431698054779633684": {
            "xp": 77,
            "level": 0
        }
    },
    "1436901011179569298": {
        "1470543411902808229": {
            "xp": 20,
            "level": 0
        }
    }
}